hydroserverpy/__init__.py
hydroserverpy/api/__init__.py
hydroserverpy/api/client.py
hydroserverpy/api/utils.py
hydroserverpy/api/models/__init__.py
hydroserverpy/api/models/base.py
hydroserverpy/api/models/etl/__init__.py
hydroserverpy/api/models/etl/data_connection.py
hydroserverpy/api/models/etl/mapping.py
hydroserverpy/api/models/etl/orchestration_system.py
hydroserverpy/api/models/etl/run.py
hydroserverpy/api/models/etl/schedule.py
hydroserverpy/api/models/etl/task.py
hydroserverpy/api/models/iam/__init__.py
hydroserverpy/api/models/iam/account.py
hydroserverpy/api/models/iam/apikey.py
hydroserverpy/api/models/iam/collaborator.py
hydroserverpy/api/models/iam/role.py
hydroserverpy/api/models/iam/workspace.py
hydroserverpy/api/models/sta/__init__.py
hydroserverpy/api/models/sta/datastream.py
hydroserverpy/api/models/sta/observation.py
hydroserverpy/api/models/sta/observed_property.py
hydroserverpy/api/models/sta/processing_level.py
hydroserverpy/api/models/sta/result_qualifier.py
hydroserverpy/api/models/sta/sensor.py
hydroserverpy/api/models/sta/thing.py
hydroserverpy/api/models/sta/unit.py
hydroserverpy/api/services/__init__.py
hydroserverpy/api/services/base.py
hydroserverpy/api/services/etl/__init__.py
hydroserverpy/api/services/etl/data_connection.py
hydroserverpy/api/services/etl/orchestration_system.py
hydroserverpy/api/services/etl/task.py
hydroserverpy/api/services/iam/__init__.py
hydroserverpy/api/services/iam/role.py
hydroserverpy/api/services/iam/workspace.py
hydroserverpy/api/services/sta/__init__.py
hydroserverpy/api/services/sta/datastream.py
hydroserverpy/api/services/sta/observed_property.py
hydroserverpy/api/services/sta/processing_level.py
hydroserverpy/api/services/sta/result_qualifier.py
hydroserverpy/api/services/sta/sensor.py
hydroserverpy/api/services/sta/thing.py
hydroserverpy/api/services/sta/unit.py
hydroserverpy/etl/__init__.py
hydroserverpy/etl/etl_configuration.py
hydroserverpy/etl/factories.py
hydroserverpy/etl/timestamp_parser.py
hydroserverpy-1.7.0.dist-info/licenses/LICENSE
hydroserverpy-1.7.0.dist-info/METADATA
hydroserverpy-1.7.0.dist-info/WHEEL
hydroserverpy-1.7.0.dist-info/top_level.txt
hydroserverpy-1.7.0.dist-info/zip-safe
hydroserverpy-1.7.0.dist-info/RECORD
