Metadata-Version: 2.4
Name: hydroserverpy
Version: 1.7.0
Summary: A Python client for managing HydroServer data
Requires-Python: <4,>=3.9
License-File: LICENSE
Requires-Dist: requests>=2
Requires-Dist: pydantic>=2.6
Requires-Dist: pydantic[email]>=2.6
Requires-Dist: pandas>=2.1
Requires-Dist: numpy>=1.22.4
Requires-Dist: pyyaml>=5
Requires-Dist: simplejson>=3
Requires-Dist: python-crontab>=3
Requires-Dist: python-dateutil>=2.8.2
Requires-Dist: croniter>=2.0.1
Requires-Dist: jmespath>=1.0.1
Provides-Extra: docs
Requires-Dist: sphinx_autodoc_typehints; extra == "docs"
Dynamic: license-file
